{"alert_id": "e5753e762596b7b7", "alert_type": "structuring", "severity": "high", "customer_id": "CUST004", "transaction_ids": ["TX302"], "score": 0.75, "reason": "Potential structuring pattern detected", "details": {"transaction_count": 3, "total_amount": 1465000, "patterns_detected": [{"type": "multiple_below_threshold", "count": 3, "amounts": [490000, 480000, 495000], "total": 1465000}, {"type": "rapid_deposits", "count": 3, "intervals_minutes": [9.166666666666667e-07, 9e-07]}], "threshold_amount": 500000, "suspicious": true}, "created_at": "2025-08-14T21:45:58.595122+08:00", "requires_review": true, "case_id": null}